maximyoga/__init__.py
maximyoga/_append_clipboard.py
maximyoga/_better_color_input.py
maximyoga/_better_input.py
maximyoga/_better_print.py
maximyoga/_check_params_decorator.py
maximyoga/_color_input.py
maximyoga/_key_dict.py
maximyoga/_kwargs_handler.py
maximyoga/_output_stdout.py
maximyoga/_repr_iterable.py
maximyoga/Terminal/__init__.py
maximyoga/Terminal/_choice_interface.py
maximyoga/Terminal/_cursor.py
maximyoga/Terminal/_manager.py
maximyoga/Terminal/color/__init__.py
maximyoga/Terminal/color/background/__init__.py
maximyoga/Terminal/color/background/_ansii_codes.py
maximyoga/Terminal/color/foreground/__init__.py
maximyoga/Terminal/color/foreground/_ansii_codes.py
maximyoga/_utils/__init__.py
maximyoga/_utils/_ansi_code_base.py
maximyoga/_utils/_ansi_code_base.pyi
helper_for_maxi-1.2.4.post2.dist-info/LICENSE
helper_for_maxi-1.2.4.post2.dist-info/METADATA
helper_for_maxi-1.2.4.post2.dist-info/WHEEL
helper_for_maxi-1.2.4.post2.dist-info/top_level.txt
helper_for_maxi-1.2.4.post2.dist-info/RECORD
