Metadata-Version: 2.1
Name: helper_for_maxi
Version: 1.2.4.post2
Summary: Contains all my Functions
Author: Maxi Myoga
Project-URL: Github, https://github.com/CatMaxiMyoga/helper_for_maxi
Project-URL: Changelog, https://github.com/CatMaxiMyoga/helper_for_maxi/blob/main/CHANGELOG.md
Classifier: Programming Language :: Python :: 3
Classifier: Development Status :: 3 - Alpha
Classifier: Operating System :: OS Independent
Requires-Python: >=3.12
License-File: LICENSE
Requires-Dist: pyperclip
Requires-Dist: pynput
Requires-Dist: pygetwindow
